{
  "$schema": "https://mintlify.com/schema.json",
  "name": "SUIRC20",
  "colors": {
    "primary": "#0D9373",
    "light": "#07C983",
    "dark": "#0D9373",
    "anchors": {
      "from": "#0D9373",
      "to": "#07C983"
    }
  },

  "anchors": [
    {
      "name": "Documentation",
      "icon": "book-open-cover",
      "url": "https://docs.suirc20.com"
    }
  ],
  "navigation": [
    {
      "group": "Introduction",
      "pages": ["introduction"]
    },
    {
      "group": "Indexer",
      "pages": ["indexer"]
    }
  ]
}
